etcdgo/__init__.py
etcdgo/config.py
etcdgo-1.1.0.dist-info/LICENSE
etcdgo-1.1.0.dist-info/METADATA
etcdgo-1.1.0.dist-info/WHEEL
etcdgo-1.1.0.dist-info/top_level.txt
etcdgo-1.1.0.dist-info/RECORD
