Metadata-Version: 2.1
Name: etcdgo
Version: 1.1.0
Summary: A library to push/pull configurations inside etcd databases
Home-page: https://github.com/acerv/etcdgo
Author: Andrea Cervesato
Author-email: andrea.cervesato@mailbox.org
License: UNKNOWN
Platform: UNKNOWN
Classifier: Development Status :: 4 - Beta
Classifier: License :: OSI Approved :: MIT License
Classifier: Intended Audience :: Developers
Classifier: Operating System :: MacOS :: MacOS X
Classifier: Operating System :: Microsoft :: Windows
Classifier: Operating System :: POSIX
Classifier: Programming Language :: Python :: 3 :: Only
Classifier: Programming Language :: Python :: 3.5
Classifier: Programming Language :: Python :: 3.6
Classifier: Programming Language :: Python :: 3.7
Classifier: Programming Language :: Python :: 3.8
Classifier: Topic :: Software Development :: Libraries
Classifier: Topic :: Software Development :: Testing
Classifier: Topic :: Utilities
Requires-Dist: etcd3 (<=0.12.0)
Requires-Dist: pyyaml (<=5.3.1)
Requires-Dist: flatten-dict (<=0.2.0)
